cryptocerts/__init__.py
cryptocerts/exceptions.py
cryptocerts/token.py
cryptocerts/utils.py
cryptocerts/paths/__init__.py
cryptocerts/paths/builder.py
cryptocerts/stores/__init__.py
cryptocerts/stores/certificate_store.py
cryptocerts/stores/certificates_store.py
cryptocerts/stores/exceptions.py
cryptocerts/validators/__init__.py
cryptocerts/validators/certificate_validator.py
cryptocerts/validators/enums.py
cryptocerts/validators/objects.py
cryptocerts-0.0.1a3.dist-info/METADATA
cryptocerts-0.0.1a3.dist-info/WHEEL
cryptocerts-0.0.1a3.dist-info/licenses/LICENSE
cryptocerts-0.0.1a3.dist-info/RECORD
