Metadata-Version: 2.1
Name: cryptocerts
Version: 0.0.1a3
Summary: Simpler certificate objects
Project-URL: Homepage, https://github.com/AlexanderFL/cryptocerts
Project-URL: Issues, https://github.com/AlexanderFL/cryptocerts/issues
Author-email: Alexander Freyr <alex@alexfreyr.com>
License: MIT License
License-File: LICENSE
Keywords: certificates,cryptography,validate,x509
Classifier: License :: OSI Approved :: MIT License
Classifier: Operating System :: OS Independent
Classifier: Programming Language :: Python :: 3
Requires-Python: >=3.10
Requires-Dist: cryptography
Requires-Dist: requests
